ngtextpreprocess/__init__.py
ngtextpreprocess/global_params.py
ngtextpreprocess/make_directory.py
ngtextpreprocess/replacement_dictionary.py
ngtextpreprocess/text_cleaner.py
ngtextpreprocess/text_processing.py
ngtextpreprocess-0.0.1.dist-info/LICENSE
ngtextpreprocess-0.0.1.dist-info/METADATA
ngtextpreprocess-0.0.1.dist-info/WHEEL
ngtextpreprocess-0.0.1.dist-info/top_level.txt
ngtextpreprocess-0.0.1.dist-info/RECORD
