Metadata-Version: 2.1
Name: ngtextpreprocess
Version: 0.0.1
Summary: A small text cleaning package
Home-page: https://github.com/ngenux/ngtextpreprocess.git
Download-URL: https://github.com/ngenux/ngtextpreprocess/archive/refs/tags/0.0.1.tar.gz
Author: Ngenux Solutions Pvt. Ltd.
Author-email: connect@ngenux.com
License: Creative Commons Attribution-NonCommercial-NoDerivatives 4.0 International
Project-URL: Bug Tracker, https://github.com/ngenux/ngtextpreprocess.git/issues
Classifier: Development Status :: 3 - Alpha
Classifier: Intended Audience :: Developers
Classifier: Topic :: Software Development :: Documentation
Classifier: License :: OSI Approved :: Common Public License
Classifier: Programming Language :: Python :: 3
Classifier: Programming Language :: Python :: 3.8
License-File: LICENSE
Requires-Dist: spacy
Requires-Dist: autocorrect
Requires-Dist: contractions
